{
  "UserAgent": "MobileHub/1.0",
  "Version": "1.0",
  "CredentialsProvider": {
    "CognitoIdentity": {
      "Default": {
        "PoolId": "us-east-1:ae1467f9-db20-4fa2-b043-b66689713530",
        "Region": "us-east-1"
      }
    }
  },
  "IdentityManager": {
    "Default": {}
  },
  "DynamoDBObjectMapper": {
    "Default": {
      "Region": "us-east-1"
    }
  },
  "PinpointAnalytics": {
    "Default": {
      "AppId": "18c906a262fc452d9182dec2dec6d66e",
      "Region": "us-east-1"
    }
  },
  "PinpointTargeting": {
    "Default": {
      "Region": "us-east-1"
    }
  }
}